Script/__init__.py
Script/prueba.py
art_daq-0.1.0.dist-info/LICENSE
art_daq-0.1.0.dist-info/METADATA
art_daq-0.1.0.dist-info/WHEEL
art_daq-0.1.0.dist-info/top_level.txt
art_daq-0.1.0.dist-info/RECORD
