Metadata-Version: 2.1
Name: art-daq
Version: 0.1.0
Summary: Paquete para usar la tarjeta de NI, USB-6001
Home-page: https://github.com/Julumisan/art-daq
Author: Juan Luis
Author-email: julumisan@gmail.com
License: UNKNOWN
Platform: UNKNOWN
Classifier: Development Status :: 3 - Alpha
Classifier: Intended Audience :: Education
Classifier: License :: OSI Approved :: MIT License
Classifier: Programming Language :: Python :: 3
Classifier: Programming Language :: Python :: 3.7
Classifier: Programming Language :: Python :: 3.8
Classifier: Programming Language :: Python :: 3.9
License-File: LICENSE
Requires-Dist: nidaqmx
